ps_calcs/__init__.py
ps_calcs/complexity.py
ps_calcs/density.py
ps_calcs/distance.py
ps_calcs/mhat.py
ps_calcs/opportunity_gain.py
ps_calcs/proximity.py
ps_calcs/rca.py
ps_calcs/rca_confidence.py
ps_calcs-2.0.0.dist-info/LICENSE
ps_calcs-2.0.0.dist-info/METADATA
ps_calcs-2.0.0.dist-info/WHEEL
ps_calcs-2.0.0.dist-info/top_level.txt
ps_calcs-2.0.0.dist-info/RECORD
