Metadata-Version: 2.1
Name: ps-calcs
Version: 2.0.0
Summary: Product Space calculations.
Home-page: https://github.com/alexandersimoes/ps_calcs
Author: Alexander Simoes
Author-email: simoes@mit.edu
License: MIT
Platform: any
Classifier: Programming Language :: Python :: 3
Classifier: Development Status :: 4 - Beta
Classifier: Environment :: Console
Classifier: Intended Audience :: Science/Research
Classifier: License :: OSI Approved :: MIT License
Classifier: Operating System :: OS Independent
Classifier: Programming Language :: Python
Classifier: Topic :: Scientific/Engineering
Classifier: Topic :: Scientific/Engineering :: Information Analysis
Classifier: Topic :: Scientific/Engineering :: Mathematics
